setup.py
cameo_sheet/__init__.py
cameo_sheet/base.py
cameo_sheet/cameo_sheet.py
cameo_sheet.egg-info/PKG-INFO
cameo_sheet.egg-info/SOURCES.txt
cameo_sheet.egg-info/dependency_links.txt
cameo_sheet.egg-info/requires.txt
cameo_sheet.egg-info/top_level.txt
test/test_cameo_sheet.py